[
    {
      "Lakmé": {
        "link": "/brands/beauty/lakme",
        "image": "src/assets/png/lakme.png",
        "products": [
          "Kajal",
          "Blush",
          "Lipstick",
          "Mascara",
          "Lip Balm",
          "Kajal"
        ]
      }
    },
    {
      "Maybelline": {
        "link": "/brands/cosmetics/maybelline",
        "image": "src/assets/jpeg/maybelline.jpeg",
        "products": [
          "Mascara",
          "Lip Balm",
          "Kajal",
          "Blush",
          "Lipstick"
        ]
      }
    },
    {
      "The Man Company": {
        "link": "/brands/grooming/the-man-company",
        "image": "src/assets/jpeg/mancompany.jpeg",
        "products": [
          "Beard Oil",
          "Face Wash",
          "Hair Gel",
          "Hair Wax"
        ]
      }
    },
    {
      "UrbanGabru": {
        "link": "/brands/grooming/urbangabru",
        "image": "src/assets/jpeg/urbangabru.jpeg",
        "products": [
          "Hair Wax",
          "Beard Oil",
          "Face Wash",
          "Beard Oil"
        ]
      }
    },
    {
      "Beardo": {
        "link": "/brands/grooming/beardo",
        "image": "src/assets/jpeg/beardo.jpeg",
        "products": [
          "Beard Wax",
          "Perfume",
          "Hair Serum",
          "Beard Oil"
        ]
      }
    },
    {
      "Bombay Shaving Co.": {
        "link": "/brands/grooming/bombay-shaving-co",
        "image": "src/assets/jpeg/bombayshaving.jpeg",
        "products": [
          "Shaving Foam",
          "Razor",
          "Beard Butter"
        ]
      }
    },
    {
      "e.l.f": {
        "link": "/brands/cosmetics/elf",
        "image": "src/assets/jpeg/elf.jpeg",
        "products": [
          "Concealer",
          "Primer",
          "Setting Spray"
        ]
      }
    }
  ]
  